sesr_tool/__init__.py
sesr_tool/cli.py
sesr_tool/infer_sr.py
sesr_tool/sesr_tool.py
sesr_tool/test.py
sesr_tool/utils.py
tests/__init__.py
tests/test_sesr_tool.py
sesr_tool-0.1.6.dist-info/AUTHORS.rst
sesr_tool-0.1.6.dist-info/LICENSE
sesr_tool-0.1.6.dist-info/METADATA
sesr_tool-0.1.6.dist-info/WHEEL
sesr_tool-0.1.6.dist-info/entry_points.txt
sesr_tool-0.1.6.dist-info/top_level.txt
sesr_tool-0.1.6.dist-info/RECORD
