Metadata-Version: 2.1
Name: sesr-tool
Version: 0.1.6
Summary: A python lib to implement sesr
Home-page: https://github.com/yunot/sesr_tool
Author: yunotao
Author-email: yunotao@163.com
License: MIT license
Keywords: sesr_tool
Classifier: Development Status :: 2 - Pre-Alpha
Classifier: Intended Audience :: Developers
Classifier: License :: OSI Approved :: MIT License
Classifier: Natural Language :: English
Classifier: Programming Language :: Python :: 3
Classifier: Programming Language :: Python :: 3.6
Classifier: Programming Language :: Python :: 3.7
Classifier: Programming Language :: Python :: 3.8
Requires-Python: >=3.6
License-File: LICENSE
License-File: AUTHORS.rst
Requires-Dist: Click >=7.0
Requires-Dist: tensorflow-datasets >=4.1.0
